solarlog_cli/__init__.py
solarlog_cli/py.typed
solarlog_cli/solarlog_client.py
solarlog_cli/solarlog_connector.py
solarlog_cli/solarlog_exceptions.py
solarlog_cli/solarlog_models.py
solarlog_cli-0.7.0.dist-info/METADATA
solarlog_cli-0.7.0.dist-info/WHEEL
solarlog_cli-0.7.0.dist-info/licenses/LICENSE
solarlog_cli-0.7.0.dist-info/RECORD
